MANIFEST.in
README.rst
setup.py
TracEasyOrder.egg-info/PKG-INFO
TracEasyOrder.egg-info/SOURCES.txt
TracEasyOrder.egg-info/dependency_links.txt
TracEasyOrder.egg-info/entry_points.txt
TracEasyOrder.egg-info/namespace_packages.txt
TracEasyOrder.egg-info/requires.txt
TracEasyOrder.egg-info/top_level.txt
tracext/__init__.py
tracext/easyorder/__init__.py
tracext/easyorder/web_ui.py
tracext/easyorder/htdocs/js/easyorder.js
tracext/easyorder/htdocs/js/jquery.tablednd.0.7.min.js