Metadata-Version: 1.0
Name: TracEasyOrder
Version: 0.1
Summary: Adds a nicer (JavaScript-based) UI for ordering enumerable ticket fields (severity, type, etc.) in Trac.
Home-page: https://bitbucket.org/embray/tracext.easyorder
Author: Erik Bray
Author-email: erik.m.bray@gmail.com
License: UNKNOWN
Platform: UNKNOWN
